discsocket/__init__.py
discsocket/container.py
discsocket/decorators.py
discsocket/embed.py
discsocket/socket.py
discsocket/models/__init__.py
discsocket/models/components.py
discsocket/models/context.py
discsocket/models/message.py
discsocket/models/user.py
discsocket/utils/__init__.py
discsocket/utils/cdn.py
discsocket-1.0.10.dist-info/LICENSE
discsocket-1.0.10.dist-info/METADATA
discsocket-1.0.10.dist-info/WHEEL
discsocket-1.0.10.dist-info/top_level.txt
discsocket-1.0.10.dist-info/RECORD
