Metadata-Version: 2.1
Name: discsocket
Version: 1.0.10
Summary: Python framework for Discord interactions.
Home-page: https://github.com/murillotadeo/discsocket
Author: Tadeo Murillo
License: MIT
Project-URL: Issue tracker, https://github.com/murillotadeo/discsocket/issues
Project-URL: Source, https://github.com/murillotadeo/discsocket
Platform: UNKNOWN
Classifier: License :: OSI Approved :: MIT License
Classifier: Operating System :: OS Independent
Classifier: Programming Language :: Python :: 3.8
Classifier: Programming Language :: Python :: 3.9
Requires-Python: >=3.8.0
Requires-Dist: aiohttp (<3.8.0,>=3.6.0)
